Workbook

Sheet SALARY SHEET
A1: Salary Sheet
A2: Employer Name | B2: Basic Salary | C2: DA 10% | D2: H.R.A. 15% | E2: CTC Salary | F2: PF 5% | G2: Take Home
A3: Priya | B3: 25000 | C3: =B3*10% -> 2500 | D3: =B3*15% -> 3750 | E3: =SUM(B3:D3) -> 31250 | F3: =B3*5% -> 1250 | G3: =E3-F3 -> 30000
A4: Renuga | B4: 24000 | C4: =B4*10% -> 2400 | D4: =B4*15% -> 3600 | E4: =SUM(B4:D4) -> 30000 | F4: =B4*5% -> 1200 | G4: =E4-F4 -> 28800
A5: Nandhini | B5: 23000 | C5: =B5*10% -> 2300 | D5: =B5*15% -> 3450 | E5: =SUM(B5:D5) -> 28750 | F5: =B5*5% -> 1150 | G5: =E5-F5 -> 27600
A6: Abi | B6: 22000 | C6: =B6*10% -> 2200 | D6: =B6*15% -> 3300 | E6: =SUM(B6:D6) -> 27500 | F6: =B6*5% -> 1100 | G6: =E6-F6 -> 26400
A7: Lavanya | B7: 21000 | C7: =B7*10% -> 2100 | D7: =B7*15% -> 3150 | E7: =SUM(B7:D7) -> 26250 | F7: =B7*5% -> 1050 | G7: =E7-F7 -> 25200
A8: Divya | B8: 20000 | C8: =B8*10% -> 2000 | D8: =B8*15% -> 3000 | E8: =SUM(B8:D8) -> 25000 | F8: =B8*5% -> 1000 | G8: =E8-F8 -> 24000
A9: Mini | B9: 19000 | C9: =B9*10% -> 1900 | D9: =B9*15% -> 2850 | E9: =SUM(B9:D9) -> 23750 | F9: =B9*5% -> 950 | G9: =E9-F9 -> 22800
A10: Malar | B10: 18000 | C10: =B10*10% -> 1800 | D10: =B10*15% -> 2700 | E10: =SUM(B10:D10) -> 22500 | F10: =B10*5% -> 900 | G10: =E10-F10 -> 21600
A11: Sankari | B11: 17000 | C11: =B11*10% -> 1700 | D11: =B11*15% -> 2550 | E11: =SUM(B11:D11) -> 21250 | F11: =B11*5% -> 850 | G11: =E11-F11 -> 20400
A12: Dharshini | B12: 16000 | C12: =B12*10% -> 1600 | D12: =B12*15% -> 2400 | E12: =SUM(B12:D12) -> 20000 | F12: =B12*5% -> 800 | G12: =E12-F12 -> 19200
A15: Employer Name | B15: Basic Salary | C15: DA 10% | D15: H.R.A. 15% | E15: CTC Salary | F15: PF 5% | G15: Take Home
A16: Lavanya | B16: =VLOOKUP(A16,A3:G12,2,FALSE) -> 21000 | C16: =VLOOKUP(A16,A3:G12,3,FALSE) -> 2100 | D16: =VLOOKUP(A16,A3:G12,4,FALSE) -> 3150 | E16: {=VLOOKUP(A16,A3:G12,{5,6,7},FALSE)} -> 26250 | F16: 1050 | G16: 25200

Sheet SALARY SHEET 2
A1: Salary Sheet
A2: Employer Name | B2: Basic Salary | C2: DA 15% | D2: H.R.A. 25% | E2: CTC Salary | F2: PF 5% | G2: Take Home
A3: Priya | B3: 25000 | C3: =B3*15% -> 3750 | D3: =B3*25% -> 6250 | E3: =SUM('SALARY SHEET 2'!B3:D3) -> 35000 | F3: =B3*5% -> 1250 | G3: =E3-F3 -> 33750
A4: Renuga | B4: 24000 | C4: =B4*15% -> 3600 | D4: =B4*25% -> 6000 | E4: =SUM('SALARY SHEET 2'!B4:D4) -> 33600 | F4: =B4*5% -> 1200 | G4: =E4-F4 -> 32400
A5: Nandhini | B5: 23000 | C5: =B5*15% -> 3450 | D5: =B5*25% -> 5750 | E5: =SUM('SALARY SHEET 2'!B5:D5) -> 32200 | F5: =B5*5% -> 1150 | G5: =E5-F5 -> 31050
A6: Abi | B6: 22000 | C6: =B6*15% -> 3300 | D6: =B6*25% -> 5500 | E6: =SUM('SALARY SHEET 2'!B6:D6) -> 30800 | F6: =B6*5% -> 1100 | G6: =E6-F6 -> 29700
A7: Lavanya | B7: 21000 | C7: =B7*15% -> 3150 | D7: =B7*25% -> 5250 | E7: =SUM('SALARY SHEET 2'!B7:D7) -> 29400 | F7: =B7*5% -> 1050 | G7: =E7-F7 -> 28350
A8: Divya | B8: 20000 | C8: =B8*15% -> 3000 | D8: =B8*25% -> 5000 | E8: =SUM('SALARY SHEET 2'!B8:D8) -> 28000 | F8: =B8*5% -> 1000 | G8: =E8-F8 -> 27000
A9: Mini | B9: 19000 | C9: =B9*15% -> 2850 | D9: =B9*25% -> 4750 | E9: =SUM('SALARY SHEET 2'!B9:D9) -> 26600 | F9: =B9*5% -> 950 | G9: =E9-F9 -> 25650
A10: Malar | B10: 18000 | C10: =B10*15% -> 2700 | D10: =B10*25% -> 4500 | E10: =SUM('SALARY SHEET 2'!B10:D10) -> 25200 | F10: =B10*5% -> 900 | G10: =E10-F10 -> 24300
A11: Sankari | B11: 17000 | C11: =B11*15% -> 2550 | D11: =B11*25% -> 4250 | E11: =SUM('SALARY SHEET 2'!B11:D11) -> 23800 | F11: =B11*5% -> 850 | G11: =E11-F11 -> 22950
A12: Dharshini | B12: 16000 | C12: =B12*15% -> 2400 | D12: =B12*25% -> 4000 | E12: =SUM('SALARY SHEET 2'!B12:D12) -> 22400 | F12: =B12*5% -> 800 | G12: =E12-F12 -> 21600
A13: Rathi | B13: 30000 | C13: =B13*15% -> 4500 | D13: =B13*25% -> 7500 | E13: =SUM('SALARY SHEET 2'!B13:D13) -> 42000 | F13: =B13*5% -> 1500 | G13: =E13-F13 -> 40500
A14: Janani | B14: 31000 | C14: =B14*15% -> 4650 | D14: =B14*25% -> 7750 | E14: =SUM('SALARY SHEET 2'!B14:D14) -> 43400 | F14: =B14*5% -> 1550 | G14: =E14-F14 -> 41850
... A22: Mohana Priya | B22: 29000 | C22: =B22*15% -> 4350 | D22: =B22*25% -> 7250 | E22: =SUM('SALARY SHEET 2'!B22:D22) -> 40600 | F22: =B22*5% -> 1450 | G22: =E22-F22 -> 39150

Sheet MATHEMATICAL FUNCTION
A1: MATHEMATICAL FUNCTION
A2: S.NO | B2: NAME | C2: TAMIL | D2: ENGLISH | E2: MATHS | F2: SCIENCE | G2: SOCIAL | H2: TOTAL | I2: AVERAGE | J2: MEDIAN | K2: MODE | L2: COUNT | M2: PERCENTAGE | N2: MIN | O2: MAX
A3: 1 | B3: Priya | C3: 85 | D3: 80 | E3: 99 | F3: 80 | G3: 80 | H3: =SUM(C3:G3) -> 424 | I3: =AVERAGE(C3:G3) -> 84.8 | J3: =MEDIAN(C3:G3) -> 80 | K3: =MODE(C3:G3) -> 80 | L3: =COUNT(C3:G3) -> 5 | M3: =H3/500 -> 0.848 | N3: =MIN(C3:G3) -> 80 | O3: =MAX(C3:G3) -> 99
A4: 2 | B4: Renuga | C4: 90 | D4: 80 | E4: 75 | F4: 95 | G4: 80 | H4: =SUM(C4:G4) -> 420 | I4: =AVERAGE(C4:G4) -> 84 | J4: =MEDIAN(C4:G4) -> 80 | K4: =MODE(C4:G4) -> 80 | L4: =COUNT(C4:G4) -> 5 | M4: =H4/500 -> 0.84 | N4: =MIN(C4:G4) -> 75 | O4: =MAX(C4:G4) -> 95 | S4: PERCENTAGE FUNCTION
A5: 3 | B5: Nandhini | C5: 90 | D5: 75 | E5: 73 | F5: 90 | G5: 96 | H5: =SUM(C5:G5) -> 424 | I5: =AVERAGE(C5:G5) -> 84.8 | J5: =MEDIAN(C5:G5) -> 90 | K5: =MODE(C5:G5) -> 90 | L5: =COUNT(C5:G5) -> 5 | M5: =H5/500 -> 0.848 | N5: =MIN(C5:G5) -> 73 | O5: =MAX(C5:G5) -> 96 | S5: TAMIL | T5: ENGLISH | U5: TOTAL | V5: PERCENTAGE
A6: 4 | B6: Abi | C6: 95 | D6: 80 | E6: 75 | F6: 92 | G6: 90 | H6: =SUM(C6:G6) -> 432 | I6: =AVERAGE(C6:G6) -> 86.4 | J6: =MEDIAN(C6:G6) -> 90 | K6: =MODE(C6:G6) -> #N/A | L6: =COUNT(C6:G6) -> 5 | M6: =H6/500 -> 0.864 | N6: =MIN(C6:G6) -> 75 | O6: =MAX(C6:G6) -> 95 | S6: 74 | T6: 84 | U6: =SUM(S6:T6) -> 158 | V6: =U6/200 -> 0.79
A7: 5 | B7: Lavanya | C7: 80 | D7: 85 | E7: 70 | F7: 82 | G7: 86 | H7: =SUM(C7:G7) -> 403 | I7: =AVERAGE(C7:G7) -> 80.6 | J7: =MEDIAN(C7:G7) -> 82 | K7: =MODE(C7:G7) -> #N/A | L7: =COUNT(C7:G7) -> 5 | M7: =H7/500 -> 0.806 | N7: =MIN(C7:G7) -> 70 | O7: =MAX(C7:G7) -> 86 | S7: 73 | T7: 83 | U7: =SUM(S7:T7) -> 156 | V7: =U7/200 -> 0.78
A8: 6 | B8: Divya | C8: 95 | D8: 90 | E8: 92 | F8: 89 | G8: 84 | H8: =SUM(C8:G8) -> 450 | I8: =AVERAGE(C8:G8) -> 90 | J8: =MEDIAN(C8:G8) -> 90 | K8: =MODE(C8:G8) -> #N/A | L8: =COUNT(C8:G8) -> 5 | M8: =H8/500 -> 0.9 | N8: =MIN(C8:G8) -> 84 | O8: =MAX(C8:G8) -> 95
A9: 7 | B9: Mini | C9: 85 | D9: 80 | E9: 78 | F9: 81 | G9: 79 | H9: =SUM(C9:G9) -> 403 | I9: =AVERAGE(C9:G9) -> 80.6 | J9: =MEDIAN(C9:G9) -> 80 | K9: =MODE(C9:G9) -> #N/A | L9: =COUNT(C9:G9) -> 5 | M9: =H9/500 -> 0.806 | N9: =MIN(C9:G9) -> 78 | O9: =MAX(C9:G9) -> 85
A10: 8 | B10: Malar | C10: 90 | D10: 90 | E10: 93 | F10: 90 | G10: 87 | H10: =SUM(C10:G10) -> 450 | I10: =AVERAGE(C10:G10) -> 90 | J10: =MEDIAN(C10:G10) -> 90 | K10: =MODE(C10:G10) -> 90 | L10: =COUNT(C10:G10) -> 5 | M10: =H10/500 -> 0.9 | N10: =MIN(C10:G10) -> 87 | O10: =MAX(C10:G10) -> 93 | S10: MIN FUNCTION
A11: 9 | B11: Sankari | C11: 90 | D11: 85 | E11: 85 | F11: 87 | G11: 89 | H11: =SUM(C11:G11) -> 436 | I11: =AVERAGE(C11:G11) -> 87.2 | J11: =MEDIAN(C11:G11) -> 87 | K11: =MODE(C11:G11) -> 85 | L11: =COUNT(C11:G11) -> 5 | M11: =H11/500 -> 0.872 | N11: =MIN(C11:G11) -> 85 | O11: =MAX(C11:G11) -> 90 | S11: 75 | T11: 85 | U11: 95 | V11: =MIN(S11:U11) -> 75
A12: 10 | B12: Dharshini | C12: 85 | D12: 80 | E12: 97 | F12: 83 | G12: 82 | H12: =SUM(C12:G12) -> 427 | I12: =AVERAGE(C12:G12) -> 85.4 | J12: =MEDIAN(C12:G12) -> 83 | K12: =MODE(C12:G12) -> #N/A | L12: =COUNT(C12:G12) -> 5 | M12: =H12/500 -> 0.854 | N12: =MIN(C12:G12) -> 80 | O12: =MAX(C12:G12) -> 97 | S12: 74 | T12: 84 | U12: 94 | V12: =MIN(S12:U12) -> 74
A13: 11 | B13: Rathi | C13: 98 | D13: 99 | E13: 100 | F13: 97 | G13: 92 | H13: =SUM(C13:G13) -> 486 | I13: =AVERAGE(C13:G13) -> 97.2 | J13: =MEDIAN(C13:G13) -> 98 | K13: =MODE(C13:G13) -> #N/A | L13: =COUNT(C13:G13) -> 5 | M13: =H13/500 -> 0.972 | N13: =MIN(C13:G13) -> 92 | O13: =MAX(C13:G13) -> 100 | S13: 73 | T13: 83 | U13: 93 | V13: =MIN(S13:U13) -> 73
A14: 12 | B14: Janani | C14: 90 | D14: 95 | E14: 90 | F14: 89 | G14: 85 | H14: =SUM(C14:G14) -> 449 | I14: =AVERAGE(C14:G14) -> 89.8 | J14: =MEDIAN(C14:G14) -> 90 | K14: =MODE(C14:G14) -> 90 | L14: =COUNT(C14:G14) -> 5 | M14: =H14/500 -> 0.898 | N14: =MIN(C14:G14) -> 85 | O14: =MAX(C14:G14) -> 95
A15: 13 | B15: Lalitha | C15: 80 | D15: 90 | E15: 80 | F15: 86 | G15: 83 | H15: =SUM(C15:G15) -> 419 | I15: =AVERAGE(C15:G15) -> 83.8 | J15: =MEDIAN(C15:G15) -> 83 | K15: =MODE(C15:G15) -> 80 | L15: =COUNT(C15:G15) -> 5 | M15: =H15/500 -> 0.838 | N15: =MIN(C15:G15) -> 80 | O15: =MAX(C15:G15) -> 90
A16: 14 | B16: Pavithra | C16: 80 | D16: 80 | E16: 80 | F16: 88 | G16: 81 | H16: =SUM(C16:G16) -> 409 | I16: =AVERAGE(C16:G16) -> 81.8 | J16: =MEDIAN(C16:G16) -> 80 | K16: =MODE(C16:G16) -> 80 | L16: =COUNT(C16:G16) -> 5 | M16: =H16/500 -> 0.818 | N16: =MIN(C16:G16) -> 80 | O16: =MAX(C16:G16) -> 88 | S16: MAX FUNCTION
A17: 15 | B17: Vanitha | C17: 85 | D17: 85 | E17: 95 | F17: 86 | G17: 82 | H17: =SUM(C17:G17) -> 433 | I17: =AVERAGE(C17:G17) -> 86.6 | J17: =MEDIAN(C17:G17) -> 85 | K17: =MODE(C17:G17) -> 85 | L17: =COUNT(C17:G17) -> 5 | M17: =H17/500 -> 0.866 | N17: =MIN(C17:G17) -> 82 | O17: =MAX(C17:G17) -> 95 | S17: 55 | T17: 65 | U17: 75 | V17: =MAX(S17:U17) -> 75
A18: 16 | B18: Devi | C18: 80 | D18: 80 | E18: 78 | F18: 78 | G18: 86 | H18: =SUM(C18:G18) -> 402 | I18: =AVERAGE(C18:G18) -> 80.4 | J18: =MEDIAN(C18:G18) -> 80 | K18: =MODE(C18:G18) -> 80 | L18: =COUNT(C18:G18) -> 5 | M18: =H18/500 -> 0.804 | N18: =MIN(C18:G18) -> 78 | O18: =MAX(C18:G18) -> 86 | S18: 56 | T18: 66 | U18: 76 | V18: =MAX(S18:U18) -> 76
A19: 17 | B19: Sathya | C19: 85 | D19: 80 | E19: 79 | F19: 83 | G19: 81 | H19: =SUM(C19:G19) -> 408 | I19: =AVERAGE(C19:G19) -> 81.6 | J19: =MEDIAN(C19:G19) -> 81 | K19: =MODE(C19:G19) -> #N/A | L19: =COUNT(C19:G19) -> 5 | M19: =H19/500 -> 0.816 | N19: =MIN(C19:G19) -> 79 | O19: =MAX(C19:G19) -> 85 | S19: 57 | T19: 67 | U19: 77 | V19: =MAX(S19:U19) -> 77
A20: 18 | B20: Lekha | C20: 85 | D20: 90 | E20: 85 | F20: 82 | G20: 85 | H20: =SUM(C20:G20) -> 427 | I20: =AVERAGE(C20:G20) -> 85.4 | J20: =MEDIAN(C20:G20) -> 85 | K20: =MODE(C20:G20) -> 85 | L20: =COUNT(C20:G20) -> 5 | M20: =H20/500 -> 0.854 | N20: =MIN(C20:G20) -> 82 | O20: =MAX(C20:G20) -> 90
A21: 19 | B21: Amesha | C21: 80 | D21: 80 | E21: 76 | F21: 78 | G21: 84 | H21: =SUM(C21:G21) -> 398 | I21: =AVERAGE(C21:G21) -> 79.6 | J21: =MEDIAN(C21:G21) -> 80 | K21: =MODE(C21:G21) -> 80 | L21: =COUNT(C21:G21) -> 5 | M21: =H21/500 -> 0.796 | N21: =MIN(C21:G21) -> 76 | O21: =MAX(C21:G21) -> 84
A22: 20 | B22: Mohana Priya | C22: 90 | D22: 95 | E22: 80 | F22: 93 | G22: 87 | H22: =SUM(C22:G22) -> 445 | I22: =AVERAGE(C22:G22) -> 89 | J22: =MEDIAN(C22:G22) -> 90 | K22: =MODE(C22:G22) -> #N/A | L22: =COUNT(C22:G22) -> 5 | M22: =H22/500 -> 0.89 | N22: =MIN(C22:G22) -> 80 | O22: =MAX(C22:G22) -> 95
C26: SUM FUNCTION | H26: AVERAGE FUNCTION | M26: MODE FUNCTION
C27: 78 | D27: 83 | E27: 65 | F27: =SUM(C27+D27+E27) -> 226 | H27: 75 | I27: 85 | J27: 95 | K27: =AVERAGE(H27:J27) -> 85 | M27: 80 | N27: 84 | O27: =MODE(M27:N27) -> #N/A
C28: 81 | D28: 73 | E28: 87 | F28: =SUM(C28+D28+E28) -> 241 | H28: 74 | I28: 84 | J28: 94 | K28: =AVERAGE(H28:J28) -> 84 | M28: 65 | N28: 67 | O28: =MODE(M28:N28) -> #N/A
C29: 72 | D29: 67 | E29: 82 | F29: =SUM(C29+D29+E29) -> 221 | H29: 73 | I29: 83 | J29: 93 | K29: =AVERAGE(H29:J29) -> 83 | M29: 70 | N29: 75 | O29: =MODE(M29:N29) -> #N/A
C32: SUM FUNCTION | H32: MEDIAN FUNCTION | M32: COUNT FUNCTION
C33: 75 | D33: 81 | E33: 62 | F33: =SUM(C33:E33) -> 218 | H33: 55 | I33: 65 | J33: 75 | K33: =MEDIAN(H33:J33) -> 65 | M33: 78 | N33: 83 | O33: =COUNT(M33:N33) -> 2
C34: 79 | D34: 75 | E34: 84 | F34: =SUM(C34:E34) -> 238 | H34: 56 | I34: 66 | J34: 76 | K34: =MEDIAN(H34:J34) -> 66 | M34: 81 | N34: 73 | O34: =COUNT(M34:N34) -> 2
C35: 76 | D35: 69 | E35: 83 | F35: =SUM(C35:E35) -> 228 | H35: 57 | I35: 67 | J35: 77 | K35: =MEDIAN(H35:J35) -> 67 | M35: 72 | N35: 67 | O35: =COUNT(M35:N35) -> 2

Sheet IF CONDITION
A1: IF CONDITION | K1: IFS CONDITION
A2: A(NAME) | B2: B(SALES) | C2: GOOD / BAD | D2: DISCOUNT | E2: IF SUBRACTION | K2: NAME | L2: TAMIL | M2: ENGLISH | N2: MATHS | O2: SCIENCE | P2: SOCIAL | Q2: G TAMIL | R2: G ENGLISH | S2: G MATHS | T2: G SCIENCE | U2: G SOCIAL
A3: Arun | B3: 60000 | C3: =IF(B3>=50000,"good","bad") -> good | D3: =IF(B3>B3-(B3-10%),B3) -> 60000 | E3: 20 | F3: 101 | G3: =IF(E3<=F3,(F3-E3),(E3-F3)) -> 81 | K3: Priya | L3: 85 | M3: 80 | N3: 99 | O3: 80 | P3: 80 | Q3: {=_xlfn.IFS(L3:P3<=50,"D",L3:P3<=70,"C",L3:P3<=80,"B",L3:P3<=90,"A",L3:P3<=95,"A+")} -> A | R3: B | S3: #N/A | T3: B | U3: B
A4: Nisha | B4: 70000 | C4: =IF(B4>=50000,"good","bad") -> good | D4: =IF(B4>B4-(B4-10%),B4) -> 70000 | E4: 25 | F4: 109 | G4: =IF(E4<=F4,(F4-E4),(E4-F4)) -> 84 | K4: Renuga | L4: 90 | M4: 80 | N4: 75 | O4: 95 | P4: 80 | Q4: {=_xlfn.IFS(L4:P4<=50,"D",L4:P4<=70,"C",L4:P4<=80,"B",L4:P4<=90,"A",L4:P4<=95,"A+")} -> A | R4: B | S4: B | T4: A+ | U4: B
A5: Pavi | B5: 40000 | C5: =IF(B5>=50000,"good","bad") -> bad | D5: =IF(B5>B5-(B5-10%),B5) -> 40000 | E5: 30 | F5: 108 | G5: =IF(E5<=F5,(F5-E5),(E5-F5)) -> 78 | K5: Nandhini | L5: 90 | M5: 75 | N5: 73 | O5: 90 | P5: 96 | Q5: {=_xlfn.IFS(L5:P5<=50,"D",L5:P5<=70,"C",L5:P5<=80,"B",L5:P5<=90,"A",L5:P5<=95,"A+")} -> A | R5: B | S5: B | T5: A | U5: #N/A
A6: Priya | B6: 80000 | C6: =IF(B6>=50000,"good","bad") -> good | D6: =IF(B6>B6-(B6-10%),B6) -> 80000 | E6: 33 | F6: 111 | G6: =IF(E6<=F6,(F6-E6),(E6-F6)) -> 78 | K6: Abi | L6: 95 | M6: 80 | N6: 75 | O6: 92 | P6: 90 | Q6: {=_xlfn.IFS(L6:P6<=50,"D",L6:P6<=70,"C",L6:P6<=80,"B",L6:P6<=90,"A",L6:P6<=95,"A+")} -> A+ | R6: B | S6: B | T6: A+ | U6: A
A7: Riya | B7: 90000 | C7: =IF(B7>=50000,"good","bad") -> good | D7: =IF(B7>B7-(B7-10%),B7) -> 90000 | E7: 29 | F7: 115 | G7: =IF(E7<=F7,(F7-E7),(E7-F7)) -> 86 | K7: Lavanya | L7: 80 | M7: 85 | N7: 70 | O7: 82 | P7: 86 | Q7: {=_xlfn.IFS(L7:P7<=50,"D",L7:P7<=70,"C",L7:P7<=80,"B",L7:P7<=90,"A",L7:P7<=95,"A+")} -> B | R7: A | S7: C | T7: A | U7: A
A8: Divya | B8: 50000 | C8: =IF(B8>=50000,"good","bad") -> good | D8: =IF(B8>B8-(B8-10%),B8) -> 50000 | E8: 19 | F8: 120 | G8: =IF(E8<=F8,(F8-E8),(E8-F8)) -> 101 | K8: Divya | L8: 95 | M8: 90 | N8: 92 | O8: 89 | P8: 84 | Q8: {=_xlfn.IFS(L8:P8<=50,"D",L8:P8<=70,"C",L8:P8<=80,"B",L8:P8<=90,"A",L8:P8<=95,"A+")} -> A+ | R8: A | S8: A+ | T8: A | U8: A
A9: Renuga | B9: 75000 | C9: =IF(B9>=50000,"good","bad") -> good | D9: =IF(B9>B9-(B9-10%),B9) -> 75000 | E9: 15 | F9: 125 | G9: =IF(E9<=F9,(F9-E9),(E9-F9)) -> 110 | K9: Mini | L9: 85 | M9: 80 | N9: 78 | O9: 81 | P9: 79 | Q9: {=_xlfn.IFS(L9:P9<=50,"D",L9:P9<=70,"C",L9:P9<=80,"B",L9:P9<=90,"A",L9:P9<=95,"A+")} -> A | R9: B | S9: B | T9: A | U9: B
C10: To find sales are good or bad | D10: Discount 10% | E10: 35 | F10: 105 | G10: =IF(E10<=F10,(F10-E10),(E10-F10)) -> 70 | K10: Malar | L10: 90 | M10: 90 | N10: 93 | O10: 90 | P10: 87 | Q10: {=_xlfn.IFS(L10:P10<=50,"D",L10:P10<=70,"C",L10:P10<=80,"B",L10:P10<=90,"A",L10:P10<=95,"A+")} -> A | R10: A | S10: A+ | T10: A | U10: A
K11: Sankari | L11: 90 | M11: 85 | N11: 85 | O11: 87 | P11: 89 | Q11: {=_xlfn.IFS(L11:P11<=50,"D",L11:P11<=70,"C",L11:P11<=80,"B",L11:P11<=90,"A",L11:P11<=95,"A+")} -> A | R11: A | S11: A | T11: A | U11: A
K12: Dharshini | L12: 85 | M12: 80 | N12: 97 | O12: 83 | P12: 82 | Q12: {=_xlfn.IFS(L12:P12<=50,"D",L12:P12<=70,"C",L12:P12<=80,"B",L12:P12<=90,"A",L12:P12<=95,"A+")} -> A | R12: B | S12: #N/A | T12: A | U12: A
A17: IF AND CONDITION | Q17: IF OR CONDITION
A18: ITEMS | B18: PS/2020 | C18: PS/2021 | D18: PS/2022 | E18: GOOD/BAD | G18: NAME | H18: TAMIL | I18: ENGLISH | J18: MATHS | K18: SCIENCE | L18: SOCIAL | M18: PASS/FAIL | Q18: NAME | R18: TAMIL | S18: ENGLISH | T18: MATHS | U18: SCIENCE | V18: SOCIAL | W18: PASS/FAIL
A19: Apple | B19: 80 | C19: 100 | D19: 90 | E19: =IF(AND(B19>60,C19>80,D19>100),"good","bad") -> bad | G19: Priya | H19: 85 | I19: 80 | J19: 99 | K19: 80 | L19: 80 | M19: {=IF(AND(H19:L19>=50),"PASS","FAIL")} -> PASS | Q19: Priya | R19: 85 | S19: 80 | T19: 99 | U19: 80 | V19: 80 | W19: {=IF(OR(R19:V19>=50),"PASS","FAIL")} -> PASS
A20: Banana | B20: 40 | C20: 45 | D20: 50 | E20: =IF(AND(B20>60,C20>80,D20>100),"good","bad") -> bad | G20: Renuga | H20: 90 | I20: 80 | J20: 75 | K20: 95 | L20: 80 | M20: {=IF(AND(H20:L20>=50),"PASS","FAIL")} -> PASS | Q20: Renuga | R20: 90 | S20: 80 | T20: 75 | U20: 95 | V20: 80 | W20: {=IF(OR(R20:V20>=50),"PASS","FAIL")} -> PASS
A21: Mango | B21: 100 | C21: 120 | D21: 150 | E21: =IF(AND(B21>60,C21>80,D21>100),"good","bad") -> good | G21: Nandhini | H21: 90 | I21: 75 | J21: 73 | K21: 90 | L21: 96 | M21: {=IF(AND(H21:L21>=50),"PASS","FAIL")} -> PASS | Q21: Nandhini | R21: 90 | S21: 75 | T21: 45 | U21: 90 | V21: 96 | W21: {=IF(OR(R21:V21>=50),"PASS","FAIL")} -> PASS
A22: Orange | B22: 90 | C22: 80 | D22: 100 | E22: =IF(AND(B22>60,C22>80,D22>100),"good","bad") -> bad | G22: Abi | H22: 95 | I22: 80 | J22: 45 | K22: 92 | L22: 90 | M22: {=IF(AND(H22:L22>=50),"PASS","FAIL")} -> FAIL | Q22: Abi | R22: 95 | S22: 80 | T22: 45 | U22: 92 | V22: 90 | W22: {=IF(OR(R22:V22>=50),"PASS","FAIL")} -> PASS
A23: Grapes | B23: 70 | C23: 60 | D23: 80 | E23: =IF(AND(B23>60,C23>80,D23>100),"good","bad") -> bad | G23: Lavanya | H23: 80 | I23: 85 | J23: 70 | K23: 82 | L23: 86 | M23: {=IF(AND(H23:L23>=50),"PASS","FAIL")} -> PASS | Q23: Lavanya | R23: 80 | S23: 85 | T23: 70 | U23: 82 | V23: 86 | W23: {=IF(OR(R23:V23>=50),"PASS","FAIL")} -> PASS
A24: Jackfruit | B24: 150 | C24: 180 | D24: 200 | E24: =IF(AND(B24>60,C24>80,D24>100),"good","bad") -> good | G24: Divya | H24: 95 | I24: 90 | J24: 92 | K24: 89 | L24: 84 | M24: {=IF(AND(H24:L24>=50),"PASS","FAIL")} -> PASS | Q24: Divya | R24: 95 | S24: 90 | T24: 92 | U24: 89 | V24: 84 | W24: {=IF(OR(R24:V24>=50),"PASS","FAIL")} -> PASS
A25: Pomogranet | B25: 170 | C25: 180 | D25: 200 | E25: =IF(AND(B25>60,C25>80,D25>100),"good","bad") -> good | G25: Mini | H25: 85 | I25: 47 | J25: 78 | K25: 81 | L25: 79 | M25: {=IF(AND(H25:L25>=50),"PASS","FAIL")} -> FAIL | Q25: Mini | R25: 85 | S25: 47 | T25: 78 | U25: 81 | V25: 79 | W25: {=IF(OR(R25:V25>=50),"PASS","FAIL")} -> PASS
A26: Pianapple | B26: 100 | C26: 80 | D26: 110 | E26: =IF(AND(B26>60,C26>80,D26>100),"good","bad") -> bad | G26: Malar | H26: 90 | I26: 90 | J26: 93 | K26: 90 | L26: 87 | M26: {=IF(AND(H26:L26>=50),"PASS","FAIL")} -> PASS | Q26: Malar | R26: 90 | S26: 90 | T26: 93 | U26: 90 | V26: 87 | W26: {=IF(OR(R26:V26>=50),"PASS","FAIL")} -> PASS
A27: Kiwi | B27: 100 | C27: 120 | D27: 150 | E27: =IF(AND(B27>60,C27>80,D27>100),"good","bad") -> good | G27: Sankari | H27: 90 | I27: 85 | J27: 85 | K27: 87 | L27: 89 | M27: {=IF(AND(H27:L27>=50),"PASS","FAIL")} -> PASS | Q27: Sankari | R27: 90 | S27: 85 | T27: 85 | U27: 87 | V27: 89 | W27: {=IF(OR(R27:V27>=50),"PASS","FAIL")} -> PASS
A28: Ice Apple | B28: 150 | C28: 160 | D28: 200 | E28: =IF(AND(B28>60,C28>80,D28>100),"good","bad") -> good | G28: Dharshini | H28: 85 | I28: 80 | J28: 97 | K28: 83 | L28: 82 | M28: {=IF(AND(H28:L28>=50),"PASS","FAIL")} -> PASS | Q28: Dharshini | R28: 85 | S28: 80 | T28: 97 | U28: 83 | V28: 82 | W28: {=IF(OR(R28:V28>=50),"PASS","FAIL")} -> PASS
A33: IF RANK CONDITION
A34: S.NO | B34: NAME | C34: TAMIL | D34: ENGLISH | E34: MATHS | F34: SCIENCE | G34: SOCIAL | H34: TOTAL | I34: PASS/FAIL | J34: RANK
A35: 1 | B35: Priya | C35: 85 | D35: 80 | E35: 99 | F35: 80 | G35: 80 | H35: =SUM(C35:G35) -> 424 | I35: {=IF(OR(C35:H35>=50),"PASS","FAIL")} -> PASS | J35: =IF(I35="PASS",RANK(H35,H35:H44,0),"NO RANK") -> 5
A36: 2 | B36: Renuga | C36: 90 | D36: 80 | E36: 75 | F36: 95 | G36: 80 | H36: =SUM(C36:G36) -> 420 | I36: {=IF(OR(C36:H36>=50),"PASS","FAIL")} -> PASS | J36: =IF(I36="PASS",RANK(H36,H36:H45,0),"NO RANK") -> 6
A37: 3 | B37: Nandhini | C37: 90 | D37: 75 | E37: 73 | F37: 90 | G37: 96 | H37: =SUM(C37:G37) -> 424 | I37: {=IF(OR(C37:H37>=50),"PASS","FAIL")} -> PASS | J37: =IF(I37="PASS",RANK(H37,H37:H46,0),"NO RANK") -> 5
A38: 4 | B38: Abi | C38: 95 | D38: 80 | E38: 45 | F38: 92 | G38: 90 | H38: =SUM(C38:G38) -> 402 | I38: {=IF(OR(C38:H38>=50),"PASS","FAIL")} -> PASS | J38: =IF(I38="PASS",RANK(H38,H38:H47,0),"NO RANK") -> 6
A39: 5 | B39: Lavanya | C39: 80 | D39: 85 | E39: 70 | F39: 82 | G39: 86 | H39: =SUM(C39:G39) -> 403 | I39: {=IF(OR(C39:H39>=50),"PASS","FAIL")} -> PASS | J39: =IF(I39="PASS",RANK(H39,H39:H48,0),"NO RANK") -> 5
A40: 6 | B40: Divya | C40: 95 | D40: 90 | E40: 92 | F40: 89 | G40: 84 | H40: =SUM(C40:G40) -> 450 | I40: {=IF(OR(C40:H40>=50),"PASS","FAIL")} -> PASS | J40: =IF(I40="PASS",RANK(H40,H40:H49,0),"NO RANK") -> 1
A41: 7 | B41: Mini | C41: 85 | D41: 47 | E41: 78 | F41: 81 | G41: 79 | H41: =SUM(C41:G41) -> 370 | I41: {=IF(OR(C41:H41>=50),"PASS","FAIL")} -> PASS | J41: =IF(I41="PASS",RANK(H41,H41:H50,0),"NO RANK") -> 4
A42: 8 | B42: Malar | C42: 90 | D42: 90 | E42: 93 | F42: 90 | G42: 87 | H42: =SUM(C42:G42) -> 450 | I42: {=IF(OR(C42:H42>=50),"PASS","FAIL")} -> PASS | J42: =IF(I42="PASS",RANK(H42,H42:H51,0),"NO RANK") -> 1
A43: 9 | B43: Sankari | C43: 90 | D43: 85 | E43: 85 | F43: 87 | G43: 89 | H43: =SUM(C43:G43) -> 436 | I43: {=IF(OR(C43:H43>=50),"PASS","FAIL")} -> PASS | J43: =IF(I43="PASS",RANK(H43,H43:H52,0),"NO RANK") -> 1
A44: 10 | B44: Dharshini | C44: 85 | D44: 80 | E44: 97 | F44: 83 | G44: 82 | H44: =SUM(C44:G44) -> 427 | I44: {=IF(OR(C44:H44>=50),"PASS","FAIL")} -> PASS | J44: =IF(I44="PASS",RANK(H44,H44:H53,0),"NO RANK") -> 1

Sheet FINANCIAL CALCULATION
C1: FINANCIAL CALCULATION
A3: PMT | D3: PMT
A4: Present value | B4: 500000 | D4: Present value | E4: 500000
A5: Rate | B5: 0.08 | D5: Rate | E5: 0.09
A6: nper | B6: 60 | D6: nper | E6: 60
A7: PMT | B7: =PMT(B5/12,B6,-B4) -> 10138.197 | D7: PMT | E7: =PMT(E5/12,E6,-E4) -> 10379.178
A10: FV | D10: PV
A11: Present value | B11: 5000 | D11: PMT | E11: 17088.81
A12: Rate | B12: 0.08 | D12: Rate | E12: 0.14
A13: nper | B13: 60 | D13: nper | E13: 36
A14: FV | B14: =FV(B12/12,B13,-B11) -> 367384.28 | D14: PV | E14: =FV(E12/12,E13,-E11) -> 759132.78
A17: NPER
A18: Present value | B18: 100000
A19: Rate | B19: 0.07
A20: PMT | B20: 2000
A21: NPER | B21: =NPER(B19/12,B20,-B18) -> 59.287765

Sheet TIME AND DATE
D1: TIME AND DATE
B3: TODAY | F3: WEEKDAYS
B4: =TODAY() -> 46308 | F4: Sunday is the first day
F5: 38464 | G5: =WEEKDAY(F5) -> 6
B6: NOW | F6: 39280 | G6: =WEEKDAY(F6) -> 3
B7: =NOW() -> 46308.514 | F7: 30586 | G7: =WEEKDAY(F7) -> 3
F8: 27124 | G8: =WEEKDAY(F8) -> 6
B10: DATE
B11: =DATE(2026,9,5) -> 46270 | F11: DATEDIF
F12: 38464 | G12: 38832 | H12: =DATEDIF(F12,G12,"YD") -> 3 | I12: Year
B13: DAY | F13: 39280 | G13: 39656 | H13: =DATEDIF(F13,G13,"m") -> 12 | I13: Month
B14: 38464 | C14: =DAY(B14) -> 22 | F14: 45905 | G14: 46280 | H14: =DATEDIF(F14,G14,"d") -> 375 | I14: Date
B16: MONTH
B17: 39280 | C17: =MONTH(B17) -> 7
B19: YEAR
B20: 38464 | C20: =YEAR(B20) -> 2005
B22: TIME
B23: =TIME(5,15,25) -> 0.21903935
B25: HOUR
B26: 0.72916667 | C26: =HOUR(B26) -> 17
B28: MINUTE
B29: 0.00069444444 | C29: =MINUTE(B29) -> 1
B31: SECONDS
B32: 0.042372685 | C32: =SECOND(B32) -> 1
B34: DATE VALUE
B35: =DATEVALUE("5-9-2026") -> 46270 | C35: 46270
B37: TIME VALUE
B38: =TIMEVALUE("11:28 PM") -> 0.97777778 | C38: 0.97777778

Sheet COUNT
A2: EXCEL COUNT, COUNTBLANK, COUNTIF & COUNTIFS PRACTICE
A3: NAME | B3: DEPARTMENT | C3: MARKS | D3: ATTENDANCE | E3: STATUS
A4: Aman | B4: Sales | C4: 78 | D4: 92 | E4: Pass
A5: Karan | B5: Sales | C5: 45 | D5: 75 | E5: Fail
A6: Neha | B6: IT | C6: 91 | D6: 96 | E6: Pass
A7: Rohit | B7: HR | D7: 82 | E7: Pending
A8: Pooja | B8: IT | C8: 72 | E8: Pass
A9: Vikas | B9: Sales | C9: 58 | D9: 85 | E9: Pass
A10: Simran | B10: HR | C10: 39 | D10: 70 | E10: Fail
A11: Meena | B11: Sales | D11: 89 | E11: Pending
A14: 4 CONSITIONS / QUESTIONS
A15: 1. COUNT | B15: How many numeric values are there in the Marks column? | E15: =COUNT(C4:C11) -> 6
A16: 2. COUNTBLANK | B16: How many blank cells are there in the Mark column? | E16: =COUNTBLANK(C4:C11) -> 2
A17: 3. COUNTIF | B17: How many employees belong to the Sales department? | E17: =COUNTIF(B4:B11,"sales") -> 4
A18: 4. COUNTIFS | B18: How many employees belong to the IT department and have marks greater than or equal to 80? | E18: =COUNTIFS(B4:B11,"it",C4:C11,">=80") -> 1

Sheet ELIGBLE OR NOT ELIGBLE
A2: AN EMPLOYEE WILL BE ELIGBLE FOR THE BOUNS IF THERE PERFORMANCE SCORE IS 80 OR ABOVE AND THEY HAVE ACHIVED EITHER THE SALES TARGET OR THE PROJECT TRAGET. OTHERWISE, THEY WILL BE NOT ELIGBLE.
A4: EMPLOYEE ID | B4: EMPLOYEE NAME | C4: PERFORMANCE SCORE | D4: SALES TARGET | E4: PROJECT TERGAT | F4: RESULT
A5: E001 | B5: Priya | C5: 85 | D5: Achieved | E5: Achieved | F5: =IF(AND(C5>=80,OR(D5="ACHIEVED",E5="ACHIEVED")),"ELIGBLE","NOTELIGBLE") -> ELIGBLE
A6: E002 | B6: Renuga | C6: 78 | D6: Achieved | E6: Achieved | F6: =IF(AND(C6>=80,OR(D6="ACHIEVED",E6="ACHIEVED")),"ELIGBLE","NOTELIGBLE") -> NOTELIGBLE
A7: E003 | B7: Nandhini | C7: 92 | D7: Not Achieved | E7: Achieved | F7: =IF(AND(C7>=80,OR(D7="ACHIEVED",E7="ACHIEVED")),"ELIGBLE","NOTELIGBLE") -> ELIGBLE
A8: E004 | B8: Abi | C8: 74 | D8: Not Achieved | E8: Not Achieved | F8: =IF(AND(C8>=80,OR(D8="ACHIEVED",E8="ACHIEVED")),"ELIGBLE","NOTELIGBLE") -> NOTELIGBLE
A9: E005 | B9: Lavanya | C9: 81 | D9: Achieved | E9: Not Achieved | F9: =IF(AND(C9>=80,OR(D9="ACHIEVED",E9="ACHIEVED")),"ELIGBLE","NOTELIGBLE") -> ELIGBLE
A10: E006 | B10: Divya | C10: 88 | D10: Not Achieved | E10: Not Achieved | F10: =IF(AND(C10>=80,OR(D10="ACHIEVED",E10="ACHIEVED")),"ELIGBLE","NOTELIGBLE") -> NOTELIGBLE
A11: E007 | B11: Mini | C11: 79 | D11: Achieved | E11: Achieved | F11: =IF(AND(C11>=80,OR(D11="ACHIEVED",E11="ACHIEVED")),"ELIGBLE","NOTELIGBLE") -> NOTELIGBLE
A12: E008 | B12: Malar | C12: 95 | D12: Achieved | E12: Achieved | F12: =IF(AND(C12>=80,OR(D12="ACHIEVED",E12="ACHIEVED")),"ELIGBLE","NOTELIGBLE") -> ELIGBLE
A13: E009 | B13: Sankari | C13: 83 | D13: Not Achieved | E13: Achieved | F13: =IF(AND(C13>=80,OR(D13="ACHIEVED",E13="ACHIEVED")),"ELIGBLE","NOTELIGBLE") -> ELIGBLE
A14: E010 | B14: Dharshini | C14: 69 | D14: Achieved | E14: Not Achieved | F14: =IF(AND(C14>=80,OR(D14="ACHIEVED",E14="ACHIEVED")),"ELIGBLE","NOTELIGBLE") -> NOTELIGBLE

Sheet FORMULA FOR EXCEL BEGINNERS
A1: FORMULA FOR EXCEL BEGINNERS
A2: NAME | B2: ENGLISH | C2: MATHS | D2: SCIENCE
A3: Aman | B3: 78 | C3: 83 | D3: 72
A4: Karan | B4: 92 | C4: 88 | D4: 95
A5: Neha | B5: 65 | C5: 74 | D5: 69
A6: Rohit | B6: 81 | C6: 79 | D6: 84
A7: Pooja | B7: 56 | C7: 63 | D7: 61
A8: Vikas | B8: 88 | C8: 91 | D8: 86
A9: Simran | B9: 73 | C9: 68 | D9: 77
A10: Meena | B10: 95 | C10: 94 | D10: 92
A12: MIN FORMULA | C12: =MIN(B3:B10) -> 56
A13: MAX FORMULA | C13: =MAX(B3:B10) -> 95
A14: AVERAGE FORMUL | C14: =AVERAGE(B3:B10) -> 78.5
A15: COUNT FORMULA | C15: =COUNT(B3:B10) -> 8

Sheet SUMIF VS COUNTIF VS AVERAGEIF
C1: SUMIF VS COUNTIF VS AVERAGEIF
A3: SUMIF | B3: =SUMIF(B9:B20,"rathi",E9:E20) -> 145000
A4: COUNTIF | B4: =COUNTIF(B9:B20,"janani") -> 3
A5: AVERAGEIF | B5: =AVERAGEIF(B9:B20,"sankari",E9:E20) -> 38000
A8: Date | B8: Salesperson | C8: Region | D8: Product | E8: Sales
A9: 46235 | B9: Sankari | C9: North | D9: Laptop | E9: 55000
A10: 46236 | B10: Dharshini | C10: South | D10: Mobile | E10: 28000
A11: 46237 | B11: Rathi | C11: North | D11: Laptop | E11: 62000
A12: 46238 | B12: Janani | C12: West | D12: Tablet | E12: 32000
A13: 46239 | B13: Sankari | C13: North | D13: Mobile | E13: 24000
A14: 46240 | B14: Dharshini | C14: South | D14: Laptop | E14: 58000
A15: 46241 | B15: Rathi | C15: East | D15: Mobile | E15: 26000
A16: 46242 | B16: Janani | C16: West | D16: Laptop | E16: 61000
A17: 46243 | B17: Sankari | C17: North | D17: Tablet | E17: 35000
A18: 46244 | B18: Dharshini | C18: South | D18: Mobile | E18: 22000
A19: 46245 | B19: Rathi | C19: East | D19: Laptop | E19: 57000
A20: 46246 | B20: Janani | C20: West | D20: Mobile | E20: 25000

Sheet SUMIFS_x0009__x0009_
B1: SUMIFS
A4: QUESTION | C4: FORMULA | D4: RUSULT
A5: Total sales for Dharshini in South region | C5: =SUMIFS(E8:E19,B8:B19,"DHARSHINI",C8:C19,"SOUTH") -> 108000 | D5: =SUMIFS(E8:E19,B8:B19,"DHARSHINI",C8:C19,"SOUTH") -> 108000
A7: Date | B7: Salesperson | C7: Region | D7: Product | E7: Sales
A8: 46235 | B8: Sankari | C8: North | D8: Laptop | E8: 55000
A9: 46236 | B9: Dharshini | C9: South | D9: Mobile | E9: 28000
A10: 46237 | B10: Rathi | C10: North | D10: Laptop | E10: 62000
A11: 46238 | B11: Janani | C11: West | D11: Tablet | E11: 32000
A12: 46239 | B12: Sankari | C12: North | D12: Mobile | E12: 24000
A13: 46240 | B13: Dharshini | C13: South | D13: Laptop | E13: 58000
A14: 46241 | B14: Rathi | C14: East | D14: Mobile | E14: 26000
A15: 46242 | B15: Janani | C15: West | D15: Laptop | E15: 61000
A16: 46243 | B16: Sankari | C16: North | D16: Tablet | E16: 35000
A17: 46244 | B17: Dharshini | C17: South | D17: Mobile | E17: 22000
A18: 46245 | B18: Rathi | C18: East | D18: Laptop | E18: 57000
A19: 46246 | B19: Janani | C19: West | D19: Mobile | E19: 25000

Sheet SUMIF VS SUM+FILTER FORMULA_x0009__x0009__x0009_
A1: SUMIF VS SUM+FILTER FORMULA
A3: NAME | B3: SALES | C3: RM NAME | D3: TOWN
A4: Priya | B4: 13721 | C4: Rajesh Sharma | D4: Delhi
A5: Divya | B5: 16267 | C5: Vikram Malhotra | D5: Mumbai
A6: Renuga | B6: 17273 | C6: Anita Roy | D6: Bangalore
A7: Priya | B7: 17860 | C7: Rajesh Sharma | D7: Pune
A8: Dharshini | B8: 13213 | C8: Deepak Verma | D8: Ahmedabad
A9: Divya | B9: 18689 | C9: Anita Roy | D9: Hyderabad
A10: Renuga | B10: 13645 | C10: Vikram Malhotra | D10: Chennai
A11: Priya | B11: 15182 | C11: Deepak Verma | D11: Kolkata
A12: Divya | B12: 14463 | C12: Rajesh Sharma | D12: Lucknow
A13: Priya | B13: 16592 | C13: Anita Roy | D13: Jaipur
A16: NAME | B16: TOTAL SALES | D16: SUMIF FORMULA
A17: Priya | B17: =SUMIF(A4:A13,A4,B4:B13) -> 63355 | D17: =SUMIF(A4:A13,A17,B4:B13) -> 63355
A18: Divya | B18: =SUMIF(A5:A14,A5,B5:B14) -> 49419
A19: Renuga | B19: =SUMIF(A6:A15,A6,B6:B15) -> 30918 | D19: SUM + FILTER FORMULA
A20: Dharshini | B20: =SUMIF(A7:A16,A7,B7:B16) -> 49634 | D20: {=SUM(_xlfn._xlws.FILTER(B4:B13,A4:A13=A17))} -> 63355

Sheet DATE VS EDATE FORMULA_x0009__x0009__x0009__x0009__x0009__x0009_
A1: DATE VS EDATE FORMULA
A2: EMPLOYEE | B2: YEAR | C2: MONTH | D2: DAY | E2: MONTH TO ADD | F2: DATE FORMULA | G2: EDATE FORMULA
A3: Priya | B3: 2024 | C3: 1 | D3: 15 | E3: 6 | F3: =DATE(B3,C3,D3) -> 45306 | G3: =EDATE(F3,E3) -> 45488
A4: Renuga | B4: 2018 | C4: 2 | D4: 10 | E4: 12 | F4: =DATE(B4,C4,D4) -> 43141 | G4: =EDATE(F4,E4) -> 43506
A5: Nandhini | B5: 2022 | C5: 3 | D5: 25 | E5: 9 | F5: =DATE(B5,C5,D5) -> 44645 | G5: =EDATE(F5,E5) -> 44920
A6: Abi | B6: 2024 | C6: 4 | D6: 15 | E6: 3 | F6: =DATE(B6,C6,D6) -> 45397 | G6: =EDATE(F6,E6) -> 45488
A7: Lavanya | B7: 2024 | C7: 5 | D7: 18 | E7: 6 | F7: =DATE(B7,C7,D7) -> 45430 | G7: =EDATE(F7,E7) -> 45614
A8: Divya | B8: 2021 | C8: 6 | D8: 22 | E8: 12 | F8: =DATE(B8,C8,D8) -> 44369 | G8: =EDATE(F8,E8) -> 44734
A9: Mini | B9: 2024 | C9: 7 | D9: 18 | E9: 19 | F9: =DATE(B9,C9,D9) -> 45491 | G9: =EDATE(F9,E9) -> 46071
A10: Malar | B10: 2024 | C10: 8 | D10: 14 | E10: 23 | F10: =DATE(B10,C10,D10) -> 45518 | G10: =EDATE(F10,E10) -> 46217
A11: Sankari | B11: 2021 | C11: 10 | D11: 30 | E11: 6 | F11: =DATE(B11,C11,D11) -> 44499 | G11: =EDATE(F11,E11) -> 44681
A12: Dharshini | B12: 2024 | C12: 10 | D12: 12 | E12: 12 | F12: =DATE(B12,C12,D12) -> 45577 | G12: =EDATE(F12,E12) -> 45942

Sheet VLOOKUP 1
C1: VLOOKUP
A3: EMPLOYEE ID | B3: EMPLOYEE NAME | C3: DEPARTMENT | D3: SALARY | F3: VLOOKUP Search
A4: E001 | B4: Priya | C4: Sales | D4: 22000 | F4: Enter Employee ID | G4: E003
A5: E002 | B5: Renuga | C5: IT | D5: 30000
A6: E003 | B6: Nandhini | C6: HR | D6: 32000 | F6: Name | G6: Nandhini
A7: E004 | B7: Abi | C7: Finance | D7: 27000 | F7: Department | G7: HR
A8: E005 | B8: Lavanya | C8: Operations | D8: 26000 | F8: Salary | G8: =VLOOKUP(G4,A4:D8,4,FALSE) -> 32000

Sheet VLOOKUP 2
A1: RAW DATA | F1: PAY REPORT
A3: EMPLOYEE ID | B3: LAST NAME | C3: FIRST NAME | F3: EMPLOYEE ID | G3: PAY | H3: FIRST NAME | I3: LAST NAME
A4: 110608 | B4: Doe | C4: John | F4: 990678 | G4: $84,289 | H4: =VLOOKUP(F4,A4:C16,3,FALSE) -> Brad | I4: =VLOOKUP(F4,A4:C16,2,FALSE) -> Pitt
A5: 253072 | B5: Cine | C5: Andy | F5: 830385 | G5: $1,37,670 | H5: =VLOOKUP(F5,A5:C17,3,FALSE) -> Prince | I5: =VLOOKUP(F5,A5:C17,2,FALSE) -> Williams
A6: 352711 | B6: Smith | C6: John | F6: 795574 | G6: $1,90,024 | H6: =VLOOKUP(F6,A6:C18,3,FALSE) -> Tony | I6: =VLOOKUP(F6,A6:C18,2,FALSE) -> Stark
A7: 391006 | B7: Pan | C7: Peter | F7: 580622 | G7: $1,22,604 | H7: =VLOOKUP(F7,A7:C19,3,FALSE) -> Eli | I7: =VLOOKUP(F7,A7:C19,2,FALSE) -> Manning
A8: 392128 | B8: Favre | C8: Bret | F8: 549457 | G8: $1,11,709 | H8: =VLOOKUP(F8,A8:C20,3,FALSE) -> John | I8: =VLOOKUP(F8,A8:C20,2,FALSE) -> Elway
A9: 549457 | B9: Elway | C9: John | F9: 392128 | G9: $85,931 | H9: =VLOOKUP(F9,A4:C16,3,FALSE) -> Bret | I9: =VLOOKUP(F9,A4:C16,2,FALSE) -> Favre
A10: 580622 | B10: Manning | C10: Eli | F10: 391006 | G10: $1,68,114 | H10: =VLOOKUP(F10,A4:C16,3,FALSE) -> Peter | I10: =VLOOKUP(F10,A4:C16,2,FALSE) -> Pan
A11: 602693 | B11: Vick | C11: Micheal | F11: 352711 | G11: $89,627 | H11: =VLOOKUP(F11,A4:C16,3,FALSE) -> John | I11: =VLOOKUP(F11,A4:C16,2,FALSE) -> Smith
A12: 611810 | B12: Woods | C12: Tiger | F12: 253072 | G12: $1,49,946 | H12: =VLOOKUP(F12,A4:C16,3,FALSE) -> Andy | I12: =VLOOKUP(F12,A4:C16,2,FALSE) -> Cine
A13: 612235 | B13: Jordan | C13: Micheal | F13: 612235 | G13: $1,45,893 | H13: =VLOOKUP(F13,A13:C25,3,FALSE) -> Micheal | I13: =VLOOKUP(F13,A13:C25,2,FALSE) -> Jordan
A14: 795574 | B14: Stark | C14: Tony | F14: 611810 | G14: $64,757 | H14: =VLOOKUP(F14,A4:C16,3,FALSE) -> Tiger | I14: =VLOOKUP(F14,A4:C16,2,FALSE) -> Woods
A15: 830385 | B15: Williams | C15: Prince | F15: 602693 | G15: $71,478 | H15: =VLOOKUP(F15,A4:C16,3,FALSE) -> Micheal | I15: =VLOOKUP(F15,A4:C16,2,FALSE) -> Vick
A16: 990678 | B16: Pitt | C16: Brad | F16: 110608 | G16: $1,31,505 | H16: =VLOOKUP(F16,A4:C16,3,FALSE) -> John | I16: =VLOOKUP(F16,A4:C16,2,FALSE) -> Doe

Sheet VLOOKUP 3
A1: RAW DATA EXTRACT #1 | F1: PAY REPORT
A3: EMPLOYEE ID | B3: LAST NAME | C3: FIRST NAME | F3: EMPLOYEE ID | G3: PAY | H3: LAST NAME | I3: CITY
A4: 110608 | B4: Doe | C4: John | F4: 990678 | G4: $84,289 | H4: =VLOOKUP(F4,A4:C16,2,TRUE) -> Pitt | I4: =VLOOKUP(F4,A22:C34,2,TRUE) -> Austin
A5: 253072 | B5: Cine | C5: Andy | F5: 830385 | G5: $1,37,670 | H5: =VLOOKUP(F5,A5:C17,2,TRUE) -> Williams | I5: =VLOOKUP(F5,A23:C35,2,TRUE) -> Chicago
A6: 352711 | B6: Smith | C6: John | F6: 795574 | G6: $1,90,024 | H6: =VLOOKUP(F6,A6:C18,2,TRUE) -> Stark | I6: =VLOOKUP(F6,A24:C36,2,TRUE) -> Austin
A7: 391006 | B7: Pan | C7: Peter | F7: 580622 | G7: $1,22,604 | H7: =VLOOKUP(F7,A7:C19,2,TRUE) -> Manning | I7: =VLOOKUP(F7,A25:C37,2,TRUE) -> Columbus
A8: 392128 | B8: Favre | C8: Bret | F8: 549457 | G8: $1,11,709 | H8: =VLOOKUP(F8,A8:C20,2,TRUE) -> Elway | I8: =VLOOKUP(F8,A26:C38,2,TRUE) -> Tampa Bay
A9: 549457 | B9: Elway | C9: John | F9: 392128 | G9: $85,931 | H9: =VLOOKUP(F9,A4:C16,2,TRUE) -> Favre | I9: =VLOOKUP(F9,A22:C34,2,TRUE) -> Chicago
A10: 580622 | B10: Manning | C10: Eli | F10: 391006 | G10: $1,68,114 | H10: =VLOOKUP(F10,A4:C16,2,TRUE) -> Pan | I10: =VLOOKUP(F10,A22:C34,2,TRUE) -> Chicago
A11: 602693 | B11: Vick | C11: Micheal | F11: 352711 | G11: $89,627 | H11: =VLOOKUP(F11,A4:C16,2,TRUE) -> Smith | I11: =VLOOKUP(F11,A22:C34,2,TRUE) -> Tampa Bay
A12: 611810 | B12: Woods | C12: Tiger | F12: 253072 | G12: $1,49,946 | H12: =VLOOKUP(F12,A4:C16,2,TRUE) -> Cine | I12: =VLOOKUP(F12,A22:C34,2,TRUE) -> Chicago
A13: 612235 | B13: Jordan | C13: Micheal | F13: 612235 | G13: $1,45,893 | H13: =VLOOKUP(F13,A4:C16,2,TRUE) -> Jordan | I13: =VLOOKUP(F13,A31:C43,2,TRUE) -> Tampa Bay
A14: 795574 | B14: Stark | C14: Tony | F14: 611810 | G14: $64,757 | H14: =VLOOKUP(F14,A14:C26,2,TRUE) -> Chicago | I14: =VLOOKUP(F14,A22:C34,2,TRUE) -> Austin
A15: 830385 | B15: Williams | C15: Prince | F15: 602693 | G15: $71,478 | H15: =VLOOKUP(F15,A4:C16,2,TRUE) -> Vick | I15: =VLOOKUP(F15,A22:C34,2,TRUE) -> Tampa Bay
A16: 990678 | B16: Pitt | C16: Brad | F16: 110608 | G16: $1,31,505 | H16: =VLOOKUP(F16,A4:C16,2,TRUE) -> Doe | I16: =VLOOKUP(F16,A22:C34,2,TRUE) -> Columbus
A19: RAW DATA EXTRACT #2
A21: EMPLOYEE ID | B21: CITY | C21: STATE
A22: 110608 | B22: Columbus | C22: Ohio
A23: 253072 | B23: Chicago | C23: Illnosi
A24: 352711 | B24: Tampa Bay | C24: Florida
A25: 391006 | B25: Chicago | C25: Illnosi
A26: 392128 | B26: Chicago | C26: Illnosi
A27: 549457 | B27: Tampa Bay | C27: Florida
A28: 580622 | B28: Columbus | C28: Ohio
A29: 602693 | B29: Tampa Bay | C29: Florida
A30: 611810 | B30: Austin | C30: Texas
A31: 612235 | B31: Tampa Bay | C31: Florida
A32: 795574 | B32: Austin | C32: Texas
A33: 830385 | B33: Chicago | C33: Illnosi
A34: 990678 | B34: Austin | C34: Texas

Sheet VLOOKUP 4
A1: PAY BAND TABLE | E1: PAY REPORT
A3: PAY MIN | B3: PAY BAND | E3: EMPLOYEE ID | F3: PAY | G3: PAY BAND
A4: 25000 | B4: Level A | E4: 990678 | F4: 84289 | G4: =VLOOKUP(E4,A4:B8,2,TRUE) -> Level E
A5: 50000 | B5: Level B | E5: 830385 | F5: 137670 | G5: =VLOOKUP(E5,A5:B9,2,TRUE) -> Level E
A6: 75000 | B6: Level C | E6: 795574 | F6: 190024 | G6: =VLOOKUP(E6,A6:B10,2,TRUE) -> Level E
A7: 100000 | B7: Level D | E7: 580622 | F7: 122604 | G7: =VLOOKUP(E7,A7:B11,2,TRUE) -> Level E
A8: 150000 | B8: Level E | E8: 549457 | F8: 111709 | G8: =VLOOKUP(E8,A8:B12,2,TRUE) -> Level E
E9: 392128 | F9: 85931 | G9: =VLOOKUP(E9,A4:B8,2,TRUE) -> Level E
E10: 391006 | F10: 168114 | G10: =VLOOKUP(E10,A4:B8,2,TRUE) -> Level E
E11: 352711 | F11: 89627 | G11: =VLOOKUP(E11,A4:B8,2,TRUE) -> Level E
E12: 253072 | F12: 149946 | G12: =VLOOKUP(E12,A4:B8,2,TRUE) -> Level E
E13: 612235 | F13: 145893 | G13: =VLOOKUP(E13,A4:B8,2,TRUE) -> Level E
E14: 611810 | F14: 64757 | G14: =VLOOKUP(E14,A4:B8,2,TRUE) -> Level E
E15: 602693 | F15: 71478 | G15: =VLOOKUP(E15,A4:B8,2,TRUE) -> Level E
E16: 110608 | F16: 131505 | G16: =VLOOKUP(E16,A4:B8,2,TRUE) -> Level D

Sheet XLOOKUP
A1: XLOOKUP Practical
A3: EMPLOYEE ID | B3: EMPLOYEE NAME | C3: DEPARTMENT | D3: JOB ROLE | E3: SALARY | F3: LOCATION | G3: STATUS
A4: EMP101 | B4: Priya | C4: ITES | D4: Process Executive | E4: 18000 | F4: Chennai | G4: Active
A5: EMP102 | B5: Renuga | C5: HR | D5: HR Executive | E5: 22000 | F5: Chennai | G5: Active
A6: EMP103 | B6: Nandhini | C6: Finance | D6: Accounts Executive | E6: 25000 | F6: Bengaluru | G6: Active
A7: EMP104 | B7: Abi | C7: ITES | D7: Customer Support | E7: 20000 | F7: Chennai | G7: Active
A8: EMP105 | B8: Lavanya | C8: IT | D8: MIS Executive | E8: 28000 | F8: Chennai | G8: Active
A9: EMP106 | B9: Divya | C9: ITES | D9: Data Entey | E9: 17500 | F9: Coimbatore | G9: Inactive
A10: EMP107 | B10: Mini | C10: IT | D10: Support Engineer | E10: 30000 | F10: Hyderabad | G10: Active
A11: EMP108 | B11: Malar | C11: HR | D11: Recruiter | E11: 24000 | F11: Chennai | G11: Active
A12: EMP109 | B12: Sankari | C12: Finance | D12: Finance Associate | E12: 26000 | F12: Bengaluru | G12: Active
A13: EMP110 | B13: Dharshini | C13: ITES | D13: Email Support | E13: 19000 | F13: Chennai | G13: Active
A16: PRACTICAL LOOKUP
A17: Enter Employee ID | B17: EMP104 | C17: Employee Name | D17: =_xlfn.XLOOKUP(B17,A4:A13,B4:B13,"NOT FOUND") -> Abi
A18: Enter Employee ID | B18: EMP107 | C18: Department | D18: =_xlfn.XLOOKUP(B18,A4:A13,C4:C13,"NOT FOUND") -> IT
A19: Enter Employee ID | B19: EMP105 | C19: Salary | D19: =_xlfn.XLOOKUP(B19,A4:A13,E4:E13,"NOT FOUND") -> 28000
A20: Enter Employee ID | B20: EMP110 | C20: Location | D20: =_xlfn.XLOOKUP(B20,A6:A15,F4:F13,"NOT FOUND") -> Chennai
A21: Enter Employee ID | B21: EMP102 | C21: Job Role | D21: =_xlfn.XLOOKUP(B21,A4:A13,D4:D13,"NOT FOUND") -> HR Executive

Sheet HLOOKUP
A1: HLOOKUP PRACTICAL EXCEL SHEET
A3: EMPLOYEE ID | B3: EMP001 | C3: EMP002 | D3: EMP003 | E3: EMP004 | F3: EMP005
A4: EMPLOYEE NAME | B4: Priya | C4: Renuga | D4: Lavanya | E4: Nandhini | F4: Abi
A5: DEPARTMENT | B5: Salea | C5: HR | D5: ITES | E5: Finance | F5: Support
A6: MONTHLY SALARY | B6: 22000 | C6: 25000 | D6: 33000 | E6: 28000 | F6: 24000
A8: LOOKUP EMPLOYEE ID | B8: EMP003
A9: EMPLOYEE NAME | B9: =HLOOKUP(B8,B3:F6,2,FALSE) -> Lavanya
A10: DEPARTMENT | B10: =HLOOKUP(B8,B3:F6,3,FALSE) -> ITES
A11: MONTHLY SALARY | B11: =HLOOKUP(B8,B3:F6,4,FALSE) -> 33000
A14: PRODUCT | B14: P001 | C14: P002 | D14: P003 | E14: P004 | F14: P005
A15: PRODUCT NAME | B15: Keuboard | C15: Mouse | D15: Headset | E15: Monitor | F15: Webcam
A16: CATEGORY | B16: IT | C16: IT | D16: Audio | E16: Display | F16: Camera
A17: PRICE | B17: 850 | C17: 450 | D17: 1200 | E17: 9500 | F17: 1800
A19: LOOKUP PRODUCT ID | B19: P004
A20: PRODUCT NAME | B20: =HLOOKUP(B19,B14:F17,2,FALSE) -> Monitor
A21: CATEGORY | B21: =HLOOKUP(B19,B14:F17,3,FALSE) -> Display
A22: PRICE | B22: =HLOOKUP(B19,B14:F17,4,FALSE) -> 9500

Sheet LOOKUP FORMULA
A1: EMPLOYEE MASTER DATA
A3: EMPLOYEE ID | B3: EMPLOYEE NAME | C3: DEPARTMENT | D3: DESIGNATION | E3: SALARY | F3: LOCATION | G3: JOINING DATE | H3: STATUS
A4: EMP101 | B4: Priya | C4: ITES | D4: Process Executive | E4: 18000 | F4: Chennai | G4: 45453 | H4: Active
A5: EMP102 | B5: Renuga | C5: HR | D5: HR Executive | E5: 22000 | F5: Chennai | G5: 45159 | H5: Active
A6: EMP103 | B6: Nandhini | C6: Finance | D6: Accounts Executive | E6: 25000 | F6: Bengaluru | G6: 44880 | H6: Active
A7: EMP104 | B7: Abi | C7: ITES | D7: Customer Support | E7: 20000 | F7: Chennai | G7: 45299 | H7: Active
A8: EMP105 | B8: Lavanya | C8: IT | D8: MIS Executive | E8: 28000 | F8: Chennai | G8: 44396 | H8: Active
A9: EMP106 | B9: Divya | C9: ITES | D9: Data Entey | E9: 17500 | F9: Coimbatore | G9: 45012 | H9: Inactive
A10: EMP107 | B10: Mini | C10: IT | D10: Support Engineer | E10: 30000 | F10: Hyderabad | G10: 45537 | H10: Active
A11: EMP108 | B11: Malar | C11: HR | D11: Recruiter | E11: 24000 | F11: Chennai | G11: 44711 | H11: Active
A12: EMP109 | B12: Sankari | C12: Finance | D12: Finance Associate | E12: 26000 | F12: Bengaluru | G12: 45271 | H12: Active
A13: EMP110 | B13: Dharshini | C13: ITES | D13: Email Support | E13: 19000 | F13: Chennai | G13: 44109 | H13: Active
A16: VLOOKUP FORMULA
A17: EMPLOYEE ID | B17: EMPLOYEE NAME | C17: DEPARTMENT | D17: DESIGNATION | E17: SALARY | F17: LOCATION | G17: JOINING DATE | H17: STATUS
A18: EMP106 | B18: =VLOOKUP(A18,A4:H13,2,FALSE) -> Divya | C18: =VLOOKUP(A18,A4:H13,3,FALSE) -> ITES | D18: =VLOOKUP(A18,A4:H13,4,FALSE) -> Data Entey | E18: =VLOOKUP(A18,A4:H13,5,FALSE) -> 17500 | F18: =VLOOKUP(A18,A4:H13,6,FALSE) -> Coimbatore | G18: =VLOOKUP(A18,A4:H13,7,FALSE) -> 45012 | H18: =VLOOKUP(A18,A4:H13,8,FALSE) -> Inactive
A21: XLOOKUP FORMULA
A22: Enter Employee ID | B22: EMP104 | C22: Employee Name | D22: =_xlfn.XLOOKUP(B22,A4:A13,B4:B13,"not found") -> Abi
A23: Enter Employee ID | B23: EMP107 | C23: Department | D23: =_xlfn.XLOOKUP(B23,A4:A13,C4:C13,"not found") -> IT
A24: Enter Employee ID | B24: EMP105 | C24: Designation | D24: =_xlfn.XLOOKUP(B24,A4:A13,D4:D13,"not found") -> MIS Executive
A25: Enter Employee ID | B25: EMP110 | C25: Salary | D25: =_xlfn.XLOOKUP(B25,A4:A13,E4:E13,"not found") -> 19000
A26: Enter Employee ID | B26: EMP102 | C26: Location | D26: =_xlfn.XLOOKUP(B26,A4:A13,F4:F13,"not found") -> Chennai
A29: HLOOKUP FORMULA
A31: EMPLOYEE ID | B31: EMP001 | C31: EMP002 | D31: EMP003 | E31: EMP004 | F31: EMP005
A32: EMPLOYEE NAME | B32: Priya | C32: Renuga | D32: Lavanya | E32: Nandhini | F32: Abi
A33: DEPARTMENT | B33: Salea | C33: HR | D33: ITES | E33: Finance | F33: Support
A34: MONTHLY SALARY | B34: 22000 | C34: 25000 | D34: 33000 | E34: 28000 | F34: 24000
A35: DESIGNATION | B35: Process Executive | C35: HR Executive | D35: Accounts Executive | E35: Customer Support | F35: Data Entey
A36: LOCATION | B36: Chennai | C36: Bengaluru | D36: Chennai | E36: Hyderabad | F36: Coimbatore
A38: LOOKUP EMPLOYEE ID | B38: EMP003
A39: EMPLOYEE NAME | B39: =HLOOKUP(B38,B31:F36,2,FALSE) -> Lavanya
A40: DEPARTMENT | B40: =HLOOKUP(B38,B31:F36,3,FALSE) -> ITES
A41: MONTHLY SALARY | B41: =HLOOKUP(B38,B31:F36,4,FALSE) -> 33000
A42: DESIGNATION | B42: =HLOOKUP(B38,B31:F36,5,FALSE) -> Accounts Executive
A43: LOCATION | B43: =HLOOKUP(B38,B31:F36,6,FALSE) -> Chennai

Sheet INDEX FUNCTION
A1: INDEX FUNCTION
A2: NO. | B2: PRODUCT | C2: RATE | D2: 2kg | E2: 5kg | F2: 10kg
A3: 1 | B3: Wheat | C3: 22 | D3: 44 | E3: 110 | F3: 220
A4: 2 | B4: Oil | C4: 122 | D4: 244 | E4: 610 | F4: 1220
A5: 3 | B5: Sugar | C5: 50 | D5: 100 | E5: 250 | F5: 500
A6: 4 | B6: Rice | C6: 68 | D6: 136 | E6: 340 | F6: 680
A7: 5 | B7: Salt | C7: 18 | D7: 36 | E7: 90 | F7: 180
A8: 6 | B8: Corn | C8: 42 | D8: 84 | E8: 210 | F8: 420
A9: 7 | B9: Oats | C9: 190 | D9: 380 | E9: 950 | F9: 1900
A10: 8 | B10: Amaranth | C10: 60 | D10: 120 | E10: 300 | F10: 600
A11: 9 | B11: Barley | C11: 400 | D11: 800 | E11: 2000 | F11: 4000
A12: 10 | B12: Bulgur | C12: 30 | D12: 60 | E12: 150 | F12: 300
A15: INDEX FUNCTION
A16: Rice (Row) | C16: =INDEX(B3:B12,4) -> Rice
A17: Rice (Row + Col) | C17: =INDEX(B3:F12,4,3) -> 136

Sheet MATCH FUNCTION
A1: MATCH FUNCTION
A2: NO. | B2: PRODUCT | C2: RATE | D2: 2kg | E2: 5kg | F2: 10kg
A3: 1 | B3: Wheat | C3: 22 | D3: 44 | E3: 110 | F3: 220
A4: 2 | B4: Oil | C4: 122 | D4: 244 | E4: 610 | F4: 1220
A5: 3 | B5: Sugar | C5: 50 | D5: 100 | E5: 250 | F5: 500
A6: 4 | B6: Rice | C6: 68 | D6: 136 | E6: 340 | F6: 680
A7: 5 | B7: Salt | C7: 18 | D7: 36 | E7: 90 | F7: 180
A8: 6 | B8: Corn | C8: 42 | D8: 84 | E8: 210 | F8: 420
A9: 7 | B9: Oats | C9: 190 | D9: 380 | E9: 950 | F9: 1900
A10: 8 | B10: Amaranth | C10: 60 | D10: 120 | E10: 300 | F10: 600
A11: 9 | B11: Barley | C11: 400 | D11: 800 | E11: 2000 | F11: 4000
A12: 10 | B12: Bulgur | C12: 30 | D12: 60 | E12: 150 | F12: 300
A15: MATCH FUNCTION
A16: Find Rice row number | C16: =MATCH("rice",B3:B12,0) -> 4
A17: Find 10kg column | C17: =MATCH("10kg",D2:F2,0) -> 3

Sheet INDEX + MATCH
A1: INDEX + MATCH FUNCTION
A3: NO. | B3: PRODUCT | C3: RATE | D3: 2kg | E3: 5kg | F3: 10kg
A4: 1 | B4: Wheat | C4: 22 | D4: 44 | E4: 110 | F4: 220
A5: 2 | B5: Oil | C5: 122 | D5: 244 | E5: 610 | F5: 1220
A6: 3 | B6: Sugar | C6: 50 | D6: 100 | E6: 250 | F6: 500
A7: 4 | B7: Rice | C7: 68 | D7: 136 | E7: 340 | F7: 680
A8: 5 | B8: Salt | C8: 18 | D8: 36 | E8: 90 | F8: 180
A9: 6 | B9: Corn | C9: 42 | D9: 84 | E9: 210 | F9: 420
A10: 7 | B10: Oats | C10: 190 | D10: 380 | E10: 950 | F10: 1900
A11: 8 | B11: Amaranth | C11: 60 | D11: 120 | E11: 300 | F11: 600
A12: 9 | B12: Barley | C12: 400 | D12: 800 | E12: 2000 | F12: 4000
A13: 10 | B13: Bulgur | C13: 30 | D13: 60 | E13: 150 | F13: 300
A16: INDEX + MATCH FUNCTION
A17: Product | C17: Rice
A18: Weight | C18: 10kg
A19: Result | C19: =INDEX(D4:F13,MATCH(C17,B4:B13,0),MATCH(C18,D3:F3,0)) -> 680
A22: PRACTICE
A23: Find Wheat 5kg price | C23: =INDEX(D4:F13,MATCH(B4,B4:B13,0),MATCH(E3,D3:F3,0)) -> 110
A24: Find Barley 2kg price | C24: =INDEX(D4:F13,MATCH(B12,B4:B13,0),MATCH(D3,D3:F3,0)) -> 800
A25: Find Oats 10kg price | C25: =INDEX(D4:F13,MATCH(B10,B4:B13,0),MATCH(F3,D3:F3,0)) -> 1900

Sheet POVIT TABLE AND CHART
A1: POVIT TABLE AND CHART
B4: Sum of Unit Price | F4: Sum of Sales Amount | J4: Total Sum of Unit Price | K4: Total Sum of Sales Amount
B5: Keyboard | C5: Laptop | D5: Monitor | E5: Mouse | F5: Keyboard | G5: Laptop | H5: Monitor | I5: Mouse
A6: 46027 | C6: 45000 | G6: 135000 | J6: 45000 | K6: 135000
A7: Customer Support | C7: 45000 | G7: 135000 | J7: 45000 | K7: 135000
A8: 46030 | D8: 12000 | H8: 60000 | J8: 12000 | K8: 60000
A9: Sales | D9: 12000 | H9: 60000 | J9: 12000 | K9: 60000
A10: 46034 | B10: 1500 | F10: 15000 | J10: 1500 | K10: 15000
A11: Customer Support | B11: 1500 | F11: 15000 | J11: 1500 | K11: 15000
A12: 46037 | C12: 45000 | G12: 90000 | J12: 45000 | K12: 90000
A13: Technical Support | C13: 45000 | G13: 90000 | J13: 45000 | K13: 90000
A14: 46042 | E14: 800 | I14: 12000 | J14: 800 | K14: 12000
A15: Sales | E15: 800 | I15: 12000 | J15: 800 | K15: 12000
A16: 46056 | D16: 12000 | H16: 48000 | J16: 12000 | K16: 48000
A17: Customer Support | D17: 12000 | H17: 48000 | J17: 12000 | K17: 48000
A18: 46060 | C18: 45000 | G18: 90000 | J18: 45000 | K18: 90000
A19: Sales | C19: 45000 | G19: 90000 | J19: 45000 | K19: 90000
A20: 46064 | E20: 800 | I20: 16000 | J20: 800 | K20: 16000
A21: Customer Support | E21: 800 | I21: 16000 | J21: 800 | K21: 16000
A22: 46071 | B22: 1500 | F22: 18000 | J22: 1500 | K22: 18000
A23: Technical Support | B23: 1500 | F23: 18000 | J23: 1500 | K23: 18000
A24: 46077 | D24: 12000 | H24: 72000 | J24: 12000 | K24: 72000
A25: Sales | D25: 12000 | H25: 72000 | J25: 12000 | K25: 72000
A26: 46085 | C26: 45000 | G26: 45000 | J26: 45000 | K26: 45000
A27: Customer Support | C27: 45000 | G27: 45000 | J27: 45000 | K27: 45000
A28: 46090 | E28: 800 | I28: 20000 | J28: 800 | K28: 20000
A29: Sales | E29: 800 | I29: 20000 | J29: 800 | K29: 20000
A30: 46094 | D30: 12000 | H30: 36000 | J30: 12000 | K30: 36000
A31: Customer Support | D31: 12000 | H31: 36000 | J31: 12000 | K31: 36000
A32: 46098 | C32: 45000 | G32: 135000 | J32: 45000 | K32: 135000
A33: Technical Support | C33: 45000 | G33: 135000 | J33: 45000 | K33: 135000
A34: 46103 | B34: 1500 | F34: 22500 | J34: 1500 | K34: 22500
A35: Sales | B35: 1500 | F35: 22500 | J35: 1500 | K35: 22500
A36: Grand Total | B36: 4500 | C36: 225000 | D36: 48000 | E36: 2400 | F36: 55500 | G36: 495000 | H36: 216000 | I36: 48000 | J36: 279900 | K36: 814500

Sheet DATA VALIDATION AND FILTER_x0009__x0009__x0009__x0009__x0009_
A1: DATA VALIDATION AND FILTER
A2: Date | B2: Employee | C2: Department | D2: Location | E2: Product | F2: Quantity | G2: Unit Price | H2: Sales Amount
A3: 46027 | B3: Asha | C3: Customer Support | D3: Chennai | E3: Laptop | F3: 3 | G3: 45000 | H3: 135000
A4: 46030 | B4: Ravi | C4: Sales | D4: Bangalore | E4: Monitor | F4: 5 | G4: 12000 | H4: 60000
A5: 46034 | B5: Priya | C5: Customer Support | D5: Chennai | E5: Keyboard | F5: 10 | G5: 1500 | H5: 15000
A6: 46037 | B6: Kiran | C6: Technical Support | D6: Hyderabad | E6: Laptop | F6: 2 | G6: 45000 | H6: 90000
A7: 46042 | B7: Meena | C7: Sales | D7: Chennai | E7: Mouse | F7: 15 | G7: 800 | H7: 12000
A8: 46056 | B8: Asha | C8: Customer Support | D8: Bangalore | E8: Monitor | F8: 4 | G8: 12000 | H8: 48000
A9: 46060 | B9: Ravi | C9: Sales | D9: Chennai | E9: Laptop | F9: 2 | G9: 45000 | H9: 90000
A10: 46064 | B10: Priya | C10: Customer Support | D10: Hyderabad | E10: Mouse | F10: 20 | G10: 800 | H10: 16000
A11: 46071 | B11: Kiran | C11: Technical Support | D11: Bangalore | E11: Keyboard | F11: 12 | G11: 1500 | H11: 18000
A12: 46077 | B12: Meena | C12: Sales | D12: Hyderabad | E12: Monitor | F12: 6 | G12: 12000 | H12: 72000
A13: 46085 | B13: Asha | C13: Customer Support | D13: Chennai | E13: Laptop | F13: 1 | G13: 45000 | H13: 45000
A14: 46090 | B14: Ravi | C14: Sales | D14: Bangalore | E14: Mouse | F14: 25 | G14: 800 | H14: 20000
... A17: 46103 | B17: Meena | C17: Sales | D17: Chennai | E17: Keyboard | F17: 15 | G17: 1500 | H17: 22500

Sheet DATA 1
A1: SHOW TOTAL SALES AMOUNT BY DEPARTMENT
A3: Row Labels | B3: Sum of Sales Amount
A4: Customer Support | B4: 295000
A5: Sales | B5: 276500
A6: Technical Support | B6: 243000
A7: Grand Total | B7: 814500

Sheet DATA 2
A1: SHOW TOTAL SALES AMOUNT BY PRODUCT
A3: Row Labels | B3: Sum of Sales Amount
A4: Keyboard | B4: 55500
A5: Laptop | B5: 495000
A6: Monitor | B6: 216000
A7: Mouse | B7: 48000
A8: Grand Total | B8: 814500

Sheet DATA 3
A1: SHOW TOTAL QUANTITY BY LOCATION
A3: Row Labels | B3: Sum of Quantity
A4: Bangalore | B4: 46
A5: Chennai | B5: 49
A6: Hyderabad | B6: 31
A7: Grand Total | B7: 126

Sheet DATA 4
A1: SHOW SALES AMOUNT BY EMPLOYEE
A3: Row Labels | B3: Sum of Sales Amount
A4: Asha | B4: 228000
A5: Kiran | B5: 243000
A6: Meena | B6: 106500
A7: Priya | B7: 67000
A8: Ravi | B8: 170000
A9: Grand Total | B9: 814500

Sheet DATA 5
A1: SHOW MONTHLY SALES AMOUNT USING THE SATE FIELD
A3: Row Labels | B3: Sum of Sales Amount
A4: Jan | B4: 312000
A5: Feb | B5: 244000
A6: Mar | B6: 258500
A7: Grand Total | B7: 814500

Sheet DATA 6
A1: CREAT A PIVOT TABLE WITH DEPARTMENT IN ROW AND PRODUCT IN COLUMNS
A3: Sum of Quantity | B3: Column Labels
A4: Row Labels | B4: Keyboard | C4: Laptop | D4: Monitor | E4: Mouse | F4: Grand Total
A5: Customer Support | B5: 10 | C5: 4 | D5: 7 | E5: 20 | F5: 41
A6: Sales | B6: 15 | C6: 2 | D6: 11 | E6: 40 | F6: 68
A7: Technical Support | B7: 12 | C7: 5 | F7: 17
A8: Grand Total | B8: 37 | C8: 11 | D8: 18 | E8: 60 | F8: 126

Sheet SALES DATA_x0009__x0009__x0009__x0009__x0009__x0009__x0009_
A1: SALES DATA
A2: Date | B2: Employee | C2: Department | D2: Location | E2: Product | F2: Quantity | G2: Unit Price | H2: Sales Amount
A3: 46027 | B3: Asha | C3: Customer Support | D3: Chennai | E3: Laptop | F3: 3 | G3: 45000 | H3: 135000
A4: 46030 | B4: Ravi | C4: Sales | D4: Bangalore | E4: Monitor | F4: 5 | G4: 12000 | H4: 60000
A5: 46034 | B5: Priya | C5: Customer Support | D5: Chennai | E5: Keyboard | F5: 10 | G5: 1500 | H5: 15000
A6: 46037 | B6: Kiran | C6: Technical Support | D6: Hyderabad | E6: Laptop | F6: 2 | G6: 45000 | H6: 90000
A7: 46042 | B7: Meena | C7: Sales | D7: Chennai | E7: Mouse | F7: 15 | G7: 800 | H7: 12000
A8: 46056 | B8: Asha | C8: Customer Support | D8: Bangalore | E8: Monitor | F8: 4 | G8: 12000 | H8: 48000
A9: 46060 | B9: Ravi | C9: Sales | D9: Chennai | E9: Laptop | F9: 2 | G9: 45000 | H9: 90000
A10: 46064 | B10: Priya | C10: Customer Support | D10: Hyderabad | E10: Mouse | F10: 20 | G10: 800 | H10: 16000
A11: 46071 | B11: Kiran | C11: Technical Support | D11: Bangalore | E11: Keyboard | F11: 12 | G11: 1500 | H11: 18000
A12: 46077 | B12: Meena | C12: Sales | D12: Hyderabad | E12: Monitor | F12: 6 | G12: 12000 | H12: 72000
A13: 46085 | B13: Asha | C13: Customer Support | D13: Chennai | E13: Laptop | F13: 1 | G13: 45000 | H13: 45000
A14: 46090 | B14: Ravi | C14: Sales | D14: Bangalore | E14: Mouse | F14: 25 | G14: 800 | H14: 20000
... A17: 46103 | B17: Meena | C17: Sales | D17: Chennai | E17: Keyboard | F17: 15 | G17: 1500 | H17: 22500

Sheet DASHBOARD
F1: DASHBOARD

Sheet PIVOT TABLE SUMMARY
A1: PIVOT TABLE SUMMARY PRACTICE
A3: SALES BY DEPARTMENT | C3: SALES BY PRODUCT | E3: QUANTITY BY LOCATION
A4: DEPARTMENT | B4: TOTAL SALES | C4: PRODUCT | D4: TOTAL SALES | E4: LOCATION | F4: TOTAL QUANTITY
A5: Customer Support | B5: =SUMIF('SALES DATA '!C3:C17,'PIVOT TABLE SUMMARY'!A5,'SALES DATA '!H3:H17) -> 295000 | C5: Laptop | D5: =SUMIF('SALES DATA '!E3:E17,'PIVOT TABLE SUMMARY'!C5,'SALES DATA '!H3:H17) -> 495000 | E5: Chennai | F5: =SUMIF('SALES DATA '!D3:D17,'PIVOT TABLE SUMMARY'!E5,'SALES DATA '!F3:F17) -> 49
A6: Sales | B6: =SUMIF('SALES DATA '!C3:C17,'PIVOT TABLE SUMMARY'!A6,'SALES DATA '!H3:H17) -> 0 | C6: Monitor | D6: =SUMIF('SALES DATA '!E3:E17,'PIVOT TABLE SUMMARY'!C6,'SALES DATA '!H3:H17) -> 216000 | E6: Bangalore | F6: =SUMIF('SALES DATA '!D3:D17,'PIVOT TABLE SUMMARY'!E6,'SALES DATA '!F3:F17) -> 46
A7: Technical Support | B7: =SUMIF('SALES DATA '!C5:C19,'PIVOT TABLE SUMMARY'!A7,'SALES DATA '!H5:H19) -> 243000 | C7: Keyboard | D7: =SUMIF('SALES DATA '!E3:E17,'PIVOT TABLE SUMMARY'!C7,'SALES DATA '!H3:H17) -> 55500 | E7: Hyderabad | F7: =SUMIF('SALES DATA '!D3:D17,'PIVOT TABLE SUMMARY'!E7,'SALES DATA '!F3:F17) -> 31
C8: Mouse | D8: =SUMIF('SALES DATA '!E3:E17,'PIVOT TABLE SUMMARY'!C8,'SALES DATA '!H3:H17) -> 48000
